narvi/__init__.py
narvi/api/__init__.py
narvi/api/narvi_server.py
narvi/apps/monitor/__init__.py
narvi/apps/monitor/index.html
narvi/apps/monitor/monitor_app.js
narvi/apps/monitor/monitor_app.py
narvi/commands/__init__.py
narvi/commands/app2app_message.py
narvi/commands/connect_session.py
narvi/commands/create_webapp.py
narvi/commands/disconnect_session.py
narvi/commands/handler_request.py
narvi/commands/handler_response.py
narvi/commands/register_download.py
narvi/commands/session_connected.py
narvi/commands/webapp_message.py
narvi/core/__init__.py
narvi/core/monitor.py
narvi/core/registered_app.py
narvi/core/registered_service.py
narvi/core/service.py
narvi/core/session.py
narvi/core/webapp.py
narvi/services/__init__.py
narvi/services/webapp_services.py
narvi/static/__init__.py
narvi/static/narvi.js
narvi/static/narvi.png
narvi/static/narvi.svg
narvi/utils/__init__.py
narvi/utils/process_metrics.py
narvi/utils/resource_loader.py
narvi/web_servers/__init__.py
narvi/web_servers/webserver_factory.py
narvi/web_servers/builtin/__init__.py
narvi/web_servers/builtin/builtin_server.py
narvi/web_servers/builtin/ws_protocol.py
narvi/web_servers/common/__init__.py
narvi/web_servers/common/server_utils.py
narvi/web_servers/tornado/__init__.py
narvi/web_servers/tornado/tornado_server_adapter.py
narvi-0.1.3.dist-info/licenses/LICENSE
narvi-0.1.3.dist-info/METADATA
narvi-0.1.3.dist-info/WHEEL
narvi-0.1.3.dist-info/top_level.txt
narvi-0.1.3.dist-info/RECORD
