Metadata-Version: 2.4
Name: narvi
Version: 0.1.3
Summary: A lightweight Python application server
Author-email: Visual Topology <dev@visualtopology.com>
License-Expression: MIT
Project-URL: Homepage, https://visualtopology.org/narvi
Project-URL: Documentation, https://visualtopology.org/narvi
Project-URL: Repository, https://codeberg.org/visual-topology/narvi
Project-URL: Issues, https://codeberg.org/visual-topology/narvi/issues
Project-URL: Changelog, https://codeberg.org/visual-topology/hyrrokkin/src/branch/main/CHANGELOG.md
Classifier: Programming Language :: Python :: 3
Classifier: Operating System :: POSIX :: Linux
Classifier: Topic :: Software Development :: Libraries :: Application Frameworks
Classifier: Development Status :: 3 - Alpha
Requires-Python: >=3.11
License-File: LICENSE
Provides-Extra: tornado
Requires-Dist: tornado; extra == "tornado"
Dynamic: license-file
